decisionengine_modules/__init__.py
decisionengine_modules/about.py
decisionengine_modules/graphite_client.py
decisionengine_modules/load_config.py
decisionengine_modules/version.py
decisionengine_modules/AWS/__init__.py
decisionengine_modules/AWS/pandas_scratch_pad.py
decisionengine_modules/AWS/scratch
decisionengine_modules/AWS/publishers/AWS_burn_rate.py
decisionengine_modules/AWS/publishers/AWS_figure_of_merit.py
decisionengine_modules/AWS/publishers/AWS_generic_publisher.py
decisionengine_modules/AWS/publishers/AWS_price_performance.py
decisionengine_modules/AWS/publishers/__init__.py
decisionengine_modules/AWS/sources/AWSInstancePerformance.py
decisionengine_modules/AWS/sources/AWSJobLimits.py
decisionengine_modules/AWS/sources/AWSOccupancy.py
decisionengine_modules/AWS/sources/AWSSpotPrice.py
decisionengine_modules/AWS/sources/BillingInfo.py
decisionengine_modules/AWS/sources/DEAccountContants.py
decisionengine_modules/AWS/sources/FinancialParameters.py
decisionengine_modules/AWS/sources/LocalCapacity.py
decisionengine_modules/AWS/sources/__init__.py
decisionengine_modules/AWS/sources/instance_performance_sample.csv
decisionengine_modules/AWS/sources/job_limits_sample.csv
decisionengine_modules/AWS/sources/occupancy_config_sample.py
decisionengine_modules/AWS/sources/spot_price_config_sample.py
decisionengine_modules/AWS/tests/test_AWSInstancePerformance.py
decisionengine_modules/AWS/tests/test_AWSJobLimits.py
decisionengine_modules/AWS/tests/test_AWSOccupancyTransform.py
decisionengine_modules/AWS/tests/test_AWSSpotPriceTransform.py
decisionengine_modules/AWS/tests/test_AWS_figure_of_merit_publisher.py
decisionengine_modules/AWS/tests/test_AWS_price_performance_publisher.py
decisionengine_modules/AWS/tests/test_AccountConstants.py
decisionengine_modules/AWS/tests/test_FigureOfMerit.py
decisionengine_modules/AWS/tests/data/AWSOccupancyTransform_expected_acquire.csv
decisionengine_modules/AWS/tests/data/AWSSpotPriceTransform_expected_acquire.csv
hepcloud_de_modules-2.0.6rc1.dist-info/licenses/LICENSE.txt
hepcloud_de_modules-2.0.6rc1.dist-info/METADATA
hepcloud_de_modules-2.0.6rc1.dist-info/WHEEL
hepcloud_de_modules-2.0.6rc1.dist-info/top_level.txt
hepcloud_de_modules-2.0.6rc1.dist-info/zip-safe
hepcloud_de_modules-2.0.6rc1.dist-info/RECORD
